remote_local/__init__.py
remote_local/middleware.py
remote_local/temporal.py
remote_local-0.0.3.dist-info/licenses/LICENSE
remote_local-0.0.3.dist-info/METADATA
remote_local-0.0.3.dist-info/WHEEL
remote_local-0.0.3.dist-info/top_level.txt
remote_local-0.0.3.dist-info/RECORD
