Metadata-Version: 2.4
Name: remote-local
Version: 0.0.3
Summary: Expose your local FastAPI, NiceGUI, or development servers remotely — easily, reliably, and for free.
Home-page: https://github.com/puntorigen/remote-local
Author: Pablo Schaffner
Author-email: Pablo Schaffner <pablo@puntorigen.com>
License-Expression: MIT
Project-URL: Homepage, https://github.com/puntorigen/remote-local
Project-URL: Source, https://github.com/puntorigen/remote-local
Project-URL: Documentation, https://github.com/puntorigen/remote-local
Classifier: Development Status :: 3 - Alpha
Classifier: Intended Audience :: Developers
Classifier: Operating System :: OS Independent
Classifier: Programming Language :: Python :: 3
Classifier: Programming Language :: Python :: 3.8
Classifier: Framework :: FastAPI
Classifier: Framework :: AsyncIO
Requires-Python: >=3.8
License-File: LICENSE
Requires-Dist: pyngrok>=5.3.0
Requires-Dist: psutil>=5.9.0
Requires-Dist: fastapi>=0.100.0
Dynamic: author
Dynamic: home-page
Dynamic: license-file
Dynamic: requires-python
